rimsschemedrawer/__init__.py
rimsschemedrawer/app.py
rimsschemedrawer/gui.py
rimsschemedrawer/json_parser.py
rimsschemedrawer/plotter.py
rimsschemedrawer/utils.py
rimsschemedrawer/assets/__init__.py
rimsschemedrawer/assets/icon.icns
rimsschemedrawer/assets/icon.ico
rimsschemedrawer/assets/icon.svg
rimsschemedrawer-3.0.0.dist-info/METADATA
rimsschemedrawer-3.0.0.dist-info/WHEEL
rimsschemedrawer-3.0.0.dist-info/entry_points.txt
rimsschemedrawer-3.0.0.dist-info/licenses/LICENSE
rimsschemedrawer-3.0.0.dist-info/RECORD
