Metadata-Version: 2.3
Name: rimsschemedrawer
Version: 3.0.0
Summary: Drawing of RIMS schemes in python and/or with a Python GUI.
Project-URL: Homepage, https://github.com/RIMS-Code/RIMSSchemeDrawer
Project-URL: Documentation, https://github.com/RIMS-Code/RIMSSchemeDrawer
Project-URL: Repository, https://github.com/RIMS-Code/RIMSSchemeDrawer.git
Project-URL: Issues, https://github.com/RIMS-Code/RIMSSchemeDrawer/issues
Author-email: Reto Trappitsch <reto@galactic-forensics.space>
License: MIT
License-File: LICENSE
Requires-Python: >=3.8
Requires-Dist: matplotlib>=3.7.4
Requires-Dist: numpy>=1.24.4
Provides-Extra: docs
Requires-Dist: mkdocs-material>=9.5.12; extra == 'docs'
Requires-Dist: mkdocs>=1.5.3; extra == 'docs'
Requires-Dist: mkdocstrings[python]>=0.24.1; extra == 'docs'
Provides-Extra: gui
Requires-Dist: pyqt6>=6.6.1; extra == 'gui'
Requires-Dist: qtpy>=2.4.1; extra == 'gui'
